segmentio/__init__.py
segmentio/client.py
segmentio/consumer.py
segmentio/request.py
segmentio/utils.py
segmentio/version.py
segmentio/test/__init__.py
segmentio/test/client.py
segmentio/test/consumer.py
segmentio/test/module.py
segmentio/test/request.py
segmentio/test/utils.py
segmentio-1.2.8.dist-info/DESCRIPTION.rst
segmentio-1.2.8.dist-info/METADATA
segmentio-1.2.8.dist-info/RECORD
segmentio-1.2.8.dist-info/WHEEL
segmentio-1.2.8.dist-info/metadata.json
segmentio-1.2.8.dist-info/top_level.txt
